smart_open/__init__.py
smart_open/azure.py
smart_open/bytebuffer.py
smart_open/compression.py
smart_open/concurrency.py
smart_open/constants.py
smart_open/doctools.py
smart_open/gcs.py
smart_open/hdfs.py
smart_open/http.py
smart_open/local_file.py
smart_open/s3.py
smart_open/smart_open_lib.py
smart_open/ssh.py
smart_open/transport.py
smart_open/utils.py
smart_open/version.py
smart_open/webhdfs.py
braingeneers_smart_open-2023.10.6.dist-info/LICENSE
braingeneers_smart_open-2023.10.6.dist-info/METADATA
braingeneers_smart_open-2023.10.6.dist-info/WHEEL
braingeneers_smart_open-2023.10.6.dist-info/top_level.txt
braingeneers_smart_open-2023.10.6.dist-info/RECORD
