Metadata-Version: 2.1
Name: braingeneers-smart-open
Version: 2023.10.6
Summary: Utils for streaming large files (S3, HDFS, GCS, Azure Blob Storage, gzip, bz2...)
Home-page: https://github.com/braingeneers/smart_open
Download-URL: http://pypi.python.org/pypi/braingeneers_smart_open
Author: Radim Rehurek
Author-email: me@radimrehurek.com
Maintainer: Radim Rehurek
Maintainer-email: me@radimrehurek.com
License: MIT
Keywords: file streaming,s3,hdfs,gcs,azure blob storage
Platform: any
Classifier: Development Status :: 4 - Beta
Classifier: Environment :: Console
Classifier: Intended Audience :: Developers
Classifier: License :: OSI Approved :: MIT License
Classifier: Operating System :: OS Independent
Classifier: Programming Language :: Python :: 3.7
Classifier: Programming Language :: Python :: 3.8
Classifier: Programming Language :: Python :: 3.9
Classifier: Programming Language :: Python :: 3.10
Classifier: Topic :: System :: Distributed Computing
Classifier: Topic :: Database :: Front-Ends
Requires-Python: >=3.6,<4.0
License-File: LICENSE
Provides-Extra: all
Requires-Dist: boto3 ; extra == 'all'
Requires-Dist: google-cloud-storage >=1.31.0 ; extra == 'all'
Requires-Dist: azure-storage-blob ; extra == 'all'
Requires-Dist: azure-common ; extra == 'all'
Requires-Dist: azure-core ; extra == 'all'
Requires-Dist: requests ; extra == 'all'
Provides-Extra: azure
Requires-Dist: azure-storage-blob ; extra == 'azure'
Requires-Dist: azure-common ; extra == 'azure'
Requires-Dist: azure-core ; extra == 'azure'
Provides-Extra: gcs
Requires-Dist: google-cloud-storage >=1.31.0 ; extra == 'gcs'
Provides-Extra: http
Requires-Dist: requests ; extra == 'http'
Provides-Extra: s3
Requires-Dist: boto3 ; extra == 's3'
Provides-Extra: test
Requires-Dist: boto3 ; extra == 'test'
Requires-Dist: google-cloud-storage >=1.31.0 ; extra == 'test'
Requires-Dist: azure-storage-blob ; extra == 'test'
Requires-Dist: azure-common ; extra == 'test'
Requires-Dist: azure-core ; extra == 'test'
Requires-Dist: requests ; extra == 'test'
Requires-Dist: moto[server] ; extra == 'test'
Requires-Dist: responses ; extra == 'test'
Requires-Dist: paramiko ; extra == 'test'
Requires-Dist: pytest ; extra == 'test'
Requires-Dist: pytest-rerunfailures ; extra == 'test'
Provides-Extra: webhdfs
Requires-Dist: requests ; extra == 'webhdfs'
